ALU_MODULE/alu.v
// Create the ALU module
module alu (DATA1, DATA2, SELECT, RESULT, ZERO);

    /* Port Declaration */

    // Two, 32-bit busses for data1 and data2
    input[31:0] DATA1,DATA2;

    // 5-bit input bus for select
    input[4:0] SELECT;

    // 32-bit reg bus for the output result
    output reg [31:0] RESULT;

    // To check wheather the alu inputs are equal or not
    output reg ZERO;

    // 32-bit wires to get the result 
    wire [31:0] ADD_RESULT,
                SUB_RESULT,
                AND_RESULT,
                OR_RESULT,
                XOR_RESULT,
			    SLL_RESULT,
                SRL_RESULT,
                SRA_RESULT,
			    MUL_RESULT,
			    DIV_RESULT,
                DIVU_RESULT,
                REM_RESULT,
                REMU_RESULT,
			    SLT_RESULT,
                SLTU_RESULT,
                FORWARD_RESULT;

    wire [63:0] MULH_RESULT,
                MULHU_RESULT,
                MULHSU_RESULT;


    assign #2 ADD_RESULT = DATA1 + DATA2;
    assign #2 SUB_RESULT = DATA1 - DATA2;
    assign #1 AND_RESULT = DATA1 & DATA2;
    assign #1 OR_RESULT = DATA1 | DATA2;
    assign #1 XOR_RESULT = DATA1 ^ DATA2;

    // logical shift    ---> shift left or right, new bits set to 0
    // arithmatic shift ---> right shift only, new bits set to sign bit
    assign #1 SLL_RESULT = DATA1 << DATA2;
    assign #1 SRL_RESULT = DATA1 >> DATA2;
    assign #1 SRA_RESULT = $signed(DATA1) >>> DATA2;

    assign #3 MUL_RESULT = DATA1 * DATA2;  // lower 32 bits of the result
    assign #3 MULH_RESULT = DATA1 * DATA2; // upper 32 bits of the result
    assign #3 MULHU_RESULT = $unsigned(DATA1) * $unsigned(DATA2); // upper 32 bits of the result
    assign #3 MULHSU_RESULT = $signed(DATA1) * $unsigned(DATA2); // upper 32 bits of the result

    assign #3 DIV_RESULT = $signed(DATA1) / $signed(DATA2);
    assign #3 DIVU_RESULT = DATA1 / DATA2;
    assign #3 REM_RESULT = $signed(DATA1) % $signed(DATA2);
    assign #3 REMU_RESULT = DATA1 % DATA2;

    assign #1 SLT_RESULT = ($signed(DATA1) < $signed(DATA2)) ? 1'b1 : 1'b0;    
    assign #1 SLTU_RESULT = ($unsigned(DATA1) < $unsigned(DATA2)) ? 1'b1 : 1'b0;

    assign #1 FORWARD_RESULT = DATA1;


    // TODO: assign correct opcodes
    // Always block for assign each module values to RESULT register
    always @(*) begin
        
        case (SELECT)
            
            5'b00000 : begin 
                RESULT = ADD_RESULT;   
            end

            5'b00001 : begin 
                RESULT = SUB_RESULT;   
            end

            5'b00010 : begin 
                RESULT = AND_RESULT;   
            end

            5'b00011 : begin 
                RESULT = OR_RESULT;   
            end

            5'b00100 : begin 
                RESULT = XOR_RESULT;   
            end

            5'b00101 : begin 
                RESULT = SLL_RESULT;   
            end

            5'b00110 : begin 
                RESULT = SRL_RESULT;   
            end

            5'b00111 : begin 
                RESULT = SRA_RESULT;   
            end

            5'b01000 : begin 
                RESULT = MUL_RESULT;   
            end

            5'b01001 : begin 
                RESULT = MULH_RESULT[63:32];   
            end

            5'b01010 : begin 
                RESULT = MULHU_RESULT[63:32];   
            end

            5'b01011 : begin 
                RESULT = MULHSU_RESULT[63:32];   
            end

            5'b01100 : begin 
                RESULT = DIV_RESULT;   
            end

            5'b01101 : begin 
                RESULT = DIVU_RESULT;   
            end

            5'b01110 : begin 
                RESULT = REM_RESULT;   
            end

            5'b01111 : begin 
                RESULT = REMU_RESULT;   
            end

            5'b10000 : begin 
                RESULT = SLT_RESULT;   
            end

            5'b10001 : begin 
                RESULT = SLTU_RESULT;   
            end

            5'b10010 : begin 
                RESULT = FORWARD_RESULT;   
            end

            default: begin
                RESULT = 32'dx;
            end 
        endcase
    end

endmodule

ALU_MODULE/alu_tb.v
`include "alu.v"

module alu_tb;

reg signed [31:0] DATA1, DATA2;
reg [4:0] ALUOP;
wire signed [31:0] ALU_RESULT;
wire ZERO_OUTPUT;

alu a(DATA1, DATA2, ALUOP, ALU_RESULT, ZERO_OUTPUT);

    initial begin

        // generate files needed to plot the waveform using GTKWave
        $dumpfile("alu_wavedata.vcd");
	    $dumpvars(0,alu_tb);

        // assign values with time to input signals to see output 
        DATA1 = 32'd100;
        DATA2 = 32'd1000;
        ALUOP = 5'b00000;   // ADD

        #4
        ALUOP = 5'b00001;   // SUB

        #4
        DATA1 = 32'd5000;

        #4
        ALUOP = 5'b00010;   // AND
        DATA1 = 32'd12;
        DATA2 = 32'd10;

        #4
        ALUOP = 5'b01000;   // MUL
    
        #4
        ALUOP = 5'b01001;   // MULH

        #4
        ALUOP = 5'b00101;   // SLL
        DATA2 = 32'd2;

        #4
        ALUOP = 5'b00110;   // SRL

        #4
        ALUOP = 5'b01100;   // DIV
        DATA1 = -32'd25;
        DATA2 = 32'd3;

        #4
        ALUOP = 5'b01110;   // REM

        #4
        ALUOP = 5'b10000;   // SLT
    
        #2;

    end

    initial begin
		$monitor($time,"\tDATA1: %d, DATA2: %d, ALUOP: %b, ALURESULT: %d",DATA1,DATA2,ALUOP,ALU_RESULT);
	end

endmodule

Hardware Units/ALU Module/alu_wavedata.vcd
$date
	Thu Apr 20 00:52:10 2023
$end
$version
	Icarus Verilog
$end
$timescale
	1s
$end
$scope module alu_tb $end
$var wire 1 ! ZERO_OUTPUT $end
$var wire 32 " ALU_RESULT [31:0] $end
$var reg 5 # ALUOP [4:0] $end
$var reg 32 $ DATA1 [31:0] $end
$var reg 32 % DATA2 [31:0] $end
$scope module a $end
$var wire 32 & AND_RESULT [31:0] $end
$var wire 32 ' DATA1 [31:0] $end
$var wire 32 ( DATA2 [31:0] $end
$var wire 32 ) FORWARD_RESULT [31:0] $end
$var wire 32 * OR_RESULT [31:0] $end
$var wire 5 + SELECT [4:0] $end
$var wire 32 , XOR_RESULT [31:0] $end
$var wire 32 - SUB_RESULT [31:0] $end
$var wire 32 . SRL_RESULT [31:0] $end
$var wire 32 / SRA_RESULT [31:0] $end
$var wire 32 0 SLT_RESULT [31:0] $end
$var wire 32 1 SLTU_RESULT [31:0] $end
$var wire 32 2 SLL_RESULT [31:0] $end
$var wire 32 3 REM_RESULT [31:0] $end
$var wire 32 4 REMU_RESULT [31:0] $end
$var wire 32 5 MUL_RESULT [31:0] $end
$var wire 64 6 MULH_RESULT [63:0] $end
$var wire 64 7 MULHU_RESULT [63:0] $end
$var wire 64 8 MULHSU_RESULT [63:0] $end
$var wire 32 9 DIV_RESULT [31:0] $end
$var wire 32 : DIVU_RESULT [31:0] $end
$var wire 32 ; ADD_RESULT [31:0] $end
$var reg 32 < RESULT [31:0] $end
$var reg 1 ! ZERO $end
$upscope $end
$upscope $end
$enddefinitions $end
#0
$dumpvars
bx <
bx ;
bx :
bx 9
bx 8
bx 7
bx 6
bx 5
bx 4
bx 3
bx 2
bx 1
bx 0
bx /
bx .
bx -
bx ,
b0 +
bx *
bx )
b1111101000 (
b1100100 '
bx &
b1111101000 %
b1100100 $
b0 #
bx "
x!
$end
#1
b1110001100 ,
b1111101100 *
b1100000 &
b0 2
b0 .
b0 /
b1100100 )
b1 0
b1 1
#2
b10001001100 "
b10001001100 <
b10001001100 ;
b11111111111111111111110001111100 -
#3
b11000011010100000 5
b11000011010100000 6
b11000011010100000 7
b11000011010100000 8
b0 9
b0 :
b1100100 3
b1100100 4
#4
b11111111111111111111110001111100 "
b11111111111111111111110001111100 <
b1 #
b1 +
#8
b1001110001000 $
b1001110001000 '
#9
b1110001000 &
b1001111101000 *
b1000001100000 ,
b0 0
b0 1
b1001110001000 )
#10
b111110100000 "
b111110100000 <
b1011101110000 ;
b111110100000 -
#11
b10011000100101101000000 5
b10011000100101101000000 6
b10011000100101101000000 7
b10011000100101101000000 8
b101 9
b101 :
b0 3
b0 4
#12
b1110001000 "
b1110001000 <
b1010 %
b1010 (
b1100 $
b1100 '
b10 #
b10 +
#13
b1000 "
b1000 <
b1000 &
b1110 *
b110 ,
b11000000000000 2
b1100 )
#14
b10110 ;
b10 -
#15
b1111000 5
b1111000 6
b1111000 7
b1111000 8
b1 9
b1 :
b10 3
b10 4
#16
b1111000 "
b1111000 <
b1000 #
b1000 +
#20
b0 "
b0 <
b1001 #
b1001 +
#24
b11000000000000 "
b11000000000000 <
b10 %
b10 (
b101 #
b101 +
#25
b110000 "
b110000 <
b0 &
b1110 ,
b110000 2
b11 .
b11 /
#26
b1110 ;
b1010 -
#27
b11000 5
b11000 6
b11000 7
b11000 8
b110 9
b110 :
b0 3
b0 4
#28
b11 "
b11 <
b110 #
b110 +
#32
b110 "
b110 <
b11 %
b11 (
b11111111111111111111111111100111 $
b11111111111111111111111111100111 '
b1100 #
b1100 +
#33
b11 &
b11111111111111111111111111100111 *
b11111111111111111111111111100100 ,
b1 0
b11111111111111111111111111100111 )
b11111111111111111111111100111000 2
b11111111111111111111111111100 .
b11111111111111111111111111111100 /
#34
b11111111111111111111111111101010 ;
b11111111111111111111111111100100 -
#35
b11111111111111111111111111111000 "
b11111111111111111111111111111000 <
b11111111111111111111111110110101 5
b1011111111111111111111111110110101 6
b1011111111111111111111111110110101 7
b1011111111111111111111111110110101 8
b11111111111111111111111111111000 9
b1010101010101010101010101001101 :
b11111111111111111111111111111111 3
#36
b11111111111111111111111111111111 "
b11111111111111111111111111111111 <
b1110 #
b1110 +
#40
b1 "
b1 <
b10000 #
b10000 +
